qcmanybody/__init__.py
qcmanybody/builder.py
qcmanybody/computer.py
qcmanybody/core.py
qcmanybody/utils.py
qcmanybody/models/__init__.py
qcmanybody/models/manybody_input_pydv1.py
qcmanybody/models/manybody_output_pydv1.py
qcmanybody/models/v1/__init__.py
qcmanybody/models/v1/generalized_optimization.py
qcmanybody/models/v1/manybody_input_pydv1.py
qcmanybody/models/v1/manybody_output_pydv1.py
qcmanybody/models/v2/__init__.py
qcmanybody/models/v2/many_body.py
qcmanybody/tests/README.md
qcmanybody/tests/__init__.py
qcmanybody/tests/addons.py
qcmanybody/tests/common.py
qcmanybody/tests/generate_component_data.py
qcmanybody/tests/test_computer_he4_multilevel.py
qcmanybody/tests/test_computer_he4_singlelevel.py
qcmanybody/tests/test_computer_het4_gradient.py
qcmanybody/tests/test_core_auxiliary.py
qcmanybody/tests/test_core_multilevel.py
qcmanybody/tests/test_core_multilevel_ss.py
qcmanybody/tests/test_core_singlelevel.py
qcmanybody/tests/test_examples.py
qcmanybody/tests/test_optimization.py
qcmanybody/tests/test_schema_keywords.py
qcmanybody/tests/test_utils.py
qcmanybody/tests/utils.py
qcmanybody/tests/component_data/h2o_trimer_multi_energy_1.json.zst
qcmanybody/tests/component_data/h2o_trimer_multi_energy_2.json.zst
qcmanybody/tests/component_data/h2o_trimer_multi_gradient_1.json.zst
qcmanybody/tests/component_data/h2o_trimer_multi_gradient_2.json.zst
qcmanybody/tests/component_data/h2o_trimer_multi_hessian_1.json.zst
qcmanybody/tests/component_data/h2o_trimer_multi_hessian_2.json.zst
qcmanybody/tests/component_data/h2o_trimer_multi_ss_energy_1.json.zst
qcmanybody/tests/component_data/h2o_trimer_multi_ss_energy_2.json.zst
qcmanybody/tests/component_data/h2o_trimer_multi_ss_gradient_1.json.zst
qcmanybody/tests/component_data/h2o_trimer_multi_ss_gradient_2.json.zst
qcmanybody/tests/component_data/h2o_trimer_multi_ss_hessian_1.json.zst
qcmanybody/tests/component_data/h2o_trimer_multi_ss_hessian_2.json.zst
qcmanybody-0.5.1.dist-info/licenses/LICENSE
qcmanybody-0.5.1.dist-info/METADATA
qcmanybody-0.5.1.dist-info/WHEEL
qcmanybody-0.5.1.dist-info/top_level.txt
qcmanybody-0.5.1.dist-info/RECORD
