Metadata-Version: 2.4
Name: qcmanybody
Version: 0.5.1
Summary: QCManyBody
Author-email: Benjamin Pritchard <bpp4@vt.edu>, "Lori A. Burns" <lori.burns@gmail.com>
Project-URL: homepage, https://github.com/MolSSI/QCManyBody
Project-URL: changelog, https://github.com/MolSSI/QCManyBody/docs/changelog.md
Project-URL: documentation, https://molssi.github.io/QCManyBody/
Project-URL: issues, https://github.com/MolSSI/QCManyBody/issues
Classifier: Programming Language :: Python :: 3
Classifier: Intended Audience :: Science/Research
Classifier: Operating System :: POSIX :: Linux
Classifier: Operating System :: MacOS
Classifier: Framework :: Pydantic
Requires-Python: >=3.8
License-File: LICENSE
Requires-Dist: numpy
Requires-Dist: pydantic<3,>=1.10.17
Requires-Dist: qcelemental<0.70.0,>=0.28.0
Provides-Extra: standard
Requires-Dist: qcengine; extra == "standard"
Provides-Extra: tests
Requires-Dist: pytest; extra == "tests"
Requires-Dist: zstandard; extra == "tests"
Provides-Extra: docs
Requires-Dist: mkdocs; extra == "docs"
Requires-Dist: mkdocs-material; extra == "docs"
Requires-Dist: mkdocstrings[python]; extra == "docs"
Requires-Dist: tabulate; extra == "docs"
Provides-Extra: dev
Requires-Dist: pre-commit; extra == "dev"
Dynamic: license-file
